sootty/__init__.py
sootty/__main__.py
sootty/display.py
sootty/exceptions.py
sootty/limits.py
sootty/main.py
sootty/parser.py
sootty/save.py
sootty/utils.py
sootty/visualizer.py
sootty/wiretrace.py
sootty/static/__init__.py
sootty/static/grammar.lark
sootty/storage/__init__.py
sootty/storage/valuechange.py
sootty/storage/wire.py
sootty/storage/wiregroup.py
sootty/storage/wiretrace.py
test/__init__.py
test/test_all.py
test/test_general.py
test/test_limits.py
test/test_pyrtl.py
test/test_style.py
test/test_wires.py
sootty-1.0.dist-info/LICENSE
sootty-1.0.dist-info/METADATA
sootty-1.0.dist-info/WHEEL
sootty-1.0.dist-info/entry_points.txt
sootty-1.0.dist-info/top_level.txt
sootty-1.0.dist-info/RECORD
