Metadata-Version: 2.1
Name: sootty
Version: 1.0
Summary: Displays vcd files to the command line.
Home-page: https://github.com/Ben1152000/sootty
Author: Ben Darnell
Author-email: ben@bdarnell.com
License: BSD
Platform: UNKNOWN
Requires-Dist: lark (>=1)
Requires-Dist: pyvcd (>=0.3)
Requires-Dist: sortedcontainers (>=2.4)
Requires-Dist: PyYAML (>=6.0)
